dscrd/__init__.py
dscrd/commands/__init__.py
dscrd/commands/bot.py
dscrd/commands/command.py
dscrd/interactions/__init__.py
dscrd/interactions/interactions.py
dscrd/interactions/redirect.py
dscrd/utils/__init__.py
dscrd/utils/allowed_mention.py
dscrd/utils/component.py
dscrd/utils/embed.py
dscrd/utils/emoji.py
dscrd/utils/files.py
dscrd/utils/message.py
dscrd/webhook/__init__.py
dscrd/webhook/webhook.py
dscrd-0.0.2.dist-info/LICENSE
dscrd-0.0.2.dist-info/METADATA
dscrd-0.0.2.dist-info/WHEEL
dscrd-0.0.2.dist-info/top_level.txt
dscrd-0.0.2.dist-info/RECORD
