Metadata-Version: 2.1
Name: dscrd
Version: 0.0.2
Summary: Fast and easy to use API Wrapper for Discord.
License-File: LICENSE
Requires-Dist: requests
Requires-Dist: websockets
Requires-Dist: pynacl
